[
  {
    "slug": "lyrics-ttml",
    "repo": "ScotcsDuluka/Lyrics-TTML",
    "name": "Lyrics-TTML",
    "description": "TTML Song",
    "homepage": null,
    "stars": 0,
    "forks": 0,
    "watchers": 0,
    "openIssues": 0,
    "language": null,
    "topics": [],
    "pushedAt": "2026-07-23T21:15:01Z",
    "createdAt": "2026-07-07T21:46:58Z",
    "updatedAt": "2026-07-23T21:15:05Z",
    "archived": false,
    "defaultBranch": "main",
    "hasReadme": true,
    "readmeExcerpt": "Lyrics-TTML",
    "fetchedAt": "2026-07-24T03:30:23.078Z"
  },
  {
    "slug": "project",
    "repo": "ScotcsDuluka/Project",
    "name": "Project",
    "description": "Duluka Studio / Community",
    "homepage": "https://scotcsduluka.github.io/Project/",
    "stars": 0,
    "forks": 0,
    "watchers": 0,
    "openIssues": 0,
    "language": "TypeScript",
    "topics": [],
    "pushedAt": "2026-07-23T03:34:07Z",
    "createdAt": "2026-07-10T08:48:49Z",
    "updatedAt": "2026-07-23T03:34:11Z",
    "archived": false,
    "defaultBranch": "main",
    "hasReadme": true,
    "readmeExcerpt": "Duluka Studio — เว็บไซต์",
    "fetchedAt": "2026-07-24T03:30:23.244Z"
  },
  {
    "slug": "nvidia-shadowplay",
    "repo": "ScotcsDuluka/NVIDIA-Shadowplay",
    "name": "NVIDIA-Shadowplay",
    "description": "ShadowPlay WinForm | Inspired by NVIDIA Shadowplay",
    "homepage": "http://scotcsduluka.github.io/NVIDIA-Shadowplay/",
    "stars": 3,
    "forks": 0,
    "watchers": 3,
    "openIssues": 0,
    "language": "Visual Basic .NET",
    "topics": [
      "ffmpeg",
      "gpu",
      "nvidiashadowplay",
      "recorder",
      "shadowplay"
    ],
    "pushedAt": "2026-07-22T00:06:58Z",
    "createdAt": "2024-10-15T13:29:15Z",
    "updatedAt": "2026-07-22T00:07:02Z",
    "archived": false,
    "defaultBranch": "Master",
    "hasReadme": true,
    "readmeExcerpt": "<img src=\"https://cdn2.steamgriddb.com/icon/e8855b3528cb03d1def9803220bd3cb9/32/48x48.png\" alt=\"NVIDIA ShadowPlay Logo\" width=\"22\"> NVIDIA ShadowPlay `Custom Implementation`",
    "fetchedAt": "2026-07-24T03:30:23.245Z"
  },
  {
    "slug": "windows-10-desktop-web",
    "repo": "ScotcsDuluka/Windows-10-Desktop-Web",
    "name": "Windows-10-Desktop-Web",
    "description": null,
    "homepage": null,
    "stars": 0,
    "forks": 0,
    "watchers": 0,
    "openIssues": 0,
    "language": "TypeScript",
    "topics": [],
    "pushedAt": "2026-07-16T07:25:23Z",
    "createdAt": "2026-07-14T18:23:51Z",
    "updatedAt": "2026-07-16T07:25:29Z",
    "archived": false,
    "defaultBranch": "main",
    "hasReadme": true,
    "readmeExcerpt": "Windows 10 Desktop (Web Edition)",
    "fetchedAt": "2026-07-24T03:30:23.245Z"
  },
  {
    "slug": "mcdmods-project-plus",
    "repo": "ScotcsDuluka/MCDMods-Project-Plus",
    "name": "MCDMods-Project-Plus",
    "description": null,
    "homepage": "https://scotcsduluka.github.io/MCDMods-Project-Plus/",
    "stars": 0,
    "forks": 0,
    "watchers": 0,
    "openIssues": 0,
    "language": "Python",
    "topics": [],
    "pushedAt": "2026-07-10T09:46:29Z",
    "createdAt": "2026-06-02T18:20:55Z",
    "updatedAt": "2026-07-10T09:46:39Z",
    "archived": false,
    "defaultBranch": "main",
    "hasReadme": true,
    "readmeExcerpt": "mcd-news",
    "fetchedAt": "2026-07-24T03:30:23.245Z"
  },
  {
    "slug": "web-hyperos-launcher",
    "repo": "ScotcsDuluka/Web-HyperOS-Launcher",
    "name": "Web-HyperOS-Launcher",
    "description": null,
    "homepage": "https://scotcsduluka.github.io/Web-HyperOS-Launcher/",
    "stars": 0,
    "forks": 0,
    "watchers": 0,
    "openIssues": 0,
    "language": "HTML",
    "topics": [],
    "pushedAt": "2026-07-01T17:31:40Z",
    "createdAt": "2026-06-05T18:57:17Z",
    "updatedAt": "2026-07-01T17:31:52Z",
    "archived": false,
    "defaultBranch": "main",
    "hasReadme": false,
    "fetchedAt": "2026-07-24T03:30:23.245Z"
  },
  {
    "slug": "web-custom",
    "repo": "ScotcsDuluka/Web-Custom",
    "name": "Web-Custom",
    "description": null,
    "homepage": "https://scotcsduluka.github.io/Web-Custom/",
    "stars": 0,
    "forks": 0,
    "watchers": 0,
    "openIssues": 0,
    "language": "HTML",
    "topics": [],
    "pushedAt": "2026-06-25T04:43:59Z",
    "createdAt": "2026-04-08T11:54:16Z",
    "updatedAt": "2026-06-29T08:43:56Z",
    "archived": false,
    "defaultBranch": "main",
    "hasReadme": false,
    "fetchedAt": "2026-07-24T03:30:23.245Z"
  },
  {
    "slug": "student-statistics",
    "repo": "ScotcsDuluka/Student-Statistics",
    "name": "Student-Statistics",
    "description": "Editor Student Statistics",
    "homepage": null,
    "stars": 0,
    "forks": 0,
    "watchers": 0,
    "openIssues": 0,
    "language": null,
    "topics": [],
    "pushedAt": "2026-06-18T03:42:02Z",
    "createdAt": "2026-06-18T03:42:02Z",
    "updatedAt": "2026-06-18T03:42:02Z",
    "archived": false,
    "defaultBranch": "main",
    "hasReadme": false,
    "fetchedAt": "2026-07-24T03:30:23.245Z"
  },
  {
    "slug": "scotcsduluka",
    "repo": "ScotcsDuluka/ScotcsDuluka",
    "name": "ScotcsDuluka",
    "description": null,
    "homepage": "https://scotcsduluka.github.io/ScotcsDuluka/",
    "stars": 0,
    "forks": 0,
    "watchers": 0,
    "openIssues": 0,
    "language": "HTML",
    "topics": [],
    "pushedAt": "2026-04-26T17:39:50Z",
    "createdAt": "2025-09-06T06:06:42Z",
    "updatedAt": "2026-04-26T17:39:54Z",
    "archived": false,
    "defaultBranch": "main",
    "hasReadme": true,
    "readmeExcerpt": "ScotcsDuluka",
    "fetchedAt": "2026-07-24T03:30:23.245Z"
  },
  {
    "slug": "always-on-display-mods",
    "repo": "ScotcsDuluka/Always-On-Display-Mods",
    "name": "Always-On-Display-Mods",
    "description": "Easy AOD Tweaks on HyperOS – Just Install via Magisk 💥",
    "homepage": "https://scotcsduluka.github.io/Always-On-Display-Mods/",
    "stars": 0,
    "forks": 0,
    "watchers": 0,
    "openIssues": 0,
    "language": "HTML",
    "topics": [
      "hyperos-magisk-aod-mods-android-root-customize"
    ],
    "pushedAt": "2026-03-31T03:33:45Z",
    "createdAt": "2025-06-03T10:19:31Z",
    "updatedAt": "2026-04-05T22:14:22Z",
    "archived": false,
    "defaultBranch": "main",
    "hasReadme": true,
    "readmeExcerpt": "Supported Devices & Version",
    "fetchedAt": "2026-07-24T03:30:23.245Z"
  },
  {
    "slug": "extreme-update",
    "repo": "ScotcsDuluka/Extreme-Update",
    "name": "Extreme-Update",
    "description": "Extreme Update",
    "homepage": null,
    "stars": 0,
    "forks": 0,
    "watchers": 0,
    "openIssues": 0,
    "language": null,
    "topics": [],
    "pushedAt": "2025-05-24T05:53:52Z",
    "createdAt": "2025-03-19T14:39:15Z",
    "updatedAt": "2025-03-30T15:23:14Z",
    "archived": false,
    "defaultBranch": "main",
    "hasReadme": true,
    "readmeExcerpt": "Extreme-Update",
    "fetchedAt": "2026-07-24T03:30:23.245Z"
  }
]
